textcompat.py
textcompat-0.1.0a1.dist-info/licenses/LICENSE
textcompat-0.1.0a1.dist-info/METADATA
textcompat-0.1.0a1.dist-info/WHEEL
textcompat-0.1.0a1.dist-info/top_level.txt
textcompat-0.1.0a1.dist-info/RECORD
