Metadata-Version: 2.4
Name: textcompat
Version: 0.1.0a1
Summary: Python library handling conversions from `typing.Text` (Python 2 `unicode`, Python 3 `str`) to UTF-8, URI, stdin/stdout, and filesystem `str`s, and vice versa.
Author-email: Jifeng Wu <jifengwu2k@gmail.com>
License-Expression: MIT
Project-URL: Homepage, https://github.com/jifengwu2k/textcompat
Project-URL: Bug Tracker, https://github.com/jifengwu2k/textcompat/issues
Classifier: Programming Language :: Python :: 2
Classifier: Programming Language :: Python :: 3
Classifier: Operating System :: OS Independent
Requires-Python: >=2
License-File: LICENSE
Requires-Dist: posix-or-nt
Requires-Dist: typing; python_version < "3.5"
Dynamic: license-file
